nac_test/__init__.py
nac_test/__main__.py
nac_test/exceptions.py
nac_test/pabot.py
nac_test/robot_writer.py
nac_test/cli/__init__.py
nac_test/cli/main.py
nac_test-1.2.2.dist-info/METADATA
nac_test-1.2.2.dist-info/WHEEL
nac_test-1.2.2.dist-info/entry_points.txt
nac_test-1.2.2.dist-info/licenses/LICENSE
nac_test-1.2.2.dist-info/RECORD
